{
	"style" : {
		"text"     : "0",  /* 文本框 */
		"textarea" : "1",  /* 多行文本框 */
		"ueditor"  : "2",  /* 编辑器 */
		"radio"    : "3",  /* 单选项 */
		"checkbox" : "4",  /* 多选项 */
		"select"   : "5",  /* 下拉框 */
		"image"    : "6",  /* 单图上传 */
		"images"   : "7",  /* 多图上传 */
		"video"    : "8",  /* 视频上传 */
		"file"     : "9",  /* 附件上传 */
		"param"    : "10", /* 单参数 */
		"params"   : "11", /* 双参数 */
		"color"    : "12", /* 颜色选择器 */
		"icon"     : "13", /* 图标选择器 */
		"items"    : "14", /* 全栏选择 */
		"group"    : "15", /* 列表栏选择 */
		"feedback" : "16", /* 反馈栏选择 */
		"search"   : "17"  /* 搜索栏选择 */
	},
	"type" : {
		"about"    : "1",
		"news"     : "2",
		"product"  : "3",
		"image"    : "4",
		"download" : "5",
		"feedback" : "6",
		"search"   : "7",
		"page"     : "8",
		"tags"     : "10",
		"member"   : "11"
	},
	"only" : {
		/* "7"   : true,  是否不同语言可以建立唯一的该类型栏目 */
		"10" : true,
		"11" : true
	}
}